claude_cli/__init__.py
claude_cli/cli.py
claude_cli/config.py
claude_cli/commands/__init__.py
claude_cli/commands/chat.py
claude_cli/commands/manage.py
claude_cli/commands/query.py
claude_cli/utils/__init__.py
claude_cli/utils/client.py
claudeshell-0.2.0.dist-info/LICENSE
claudeshell-0.2.0.dist-info/METADATA
claudeshell-0.2.0.dist-info/WHEEL
claudeshell-0.2.0.dist-info/entry_points.txt
claudeshell-0.2.0.dist-info/top_level.txt
claudeshell-0.2.0.dist-info/RECORD
