Metadata-Version: 2.2
Name: claudeshell
Version: 0.2.0
Summary: A command-line interface for Claude AI
Home-page: https://github.com/soheilsh7/claude-cli
Author: soheil shabani
Author-email: soheilshabani.79.ss@gmail.com
License: MIT
Project-URL: Bug Tracker, https://github.com/soheilsh7/claude-cli/issues
Project-URL: Documentation, https://github.com/soheilsh7/claude-cli
Project-URL: Source Code, https://github.com/soheilsh7/claude-cli
Keywords: claude,ai,cli,chatbot,anthropic,command-line
Classifier: Development Status :: 3 - Alpha
Classifier: Intended Audience :: Developers
Classifier: License :: OSI Approved :: MIT License
Classifier: Programming Language :: Python :: 3.7
Classifier: Programming Language :: Python :: 3.8
Classifier: Programming Language :: Python :: 3.9
Classifier: Programming Language :: Python :: 3.10
Classifier: Programming Language :: Python :: 3.11
Classifier: Operating System :: OS Independent
Classifier: Environment :: Console
Classifier: Topic :: Utilities
Requires-Python: >=3.7
License-File: LICENSE
Requires-Dist: claude-api>=1.0.17
Requires-Dist: click>=8.0.0
Requires-Dist: rich>=12.0.0
Requires-Dist: pyyaml>=6.0
Dynamic: author
Dynamic: author-email
Dynamic: classifier
Dynamic: description
Dynamic: description-content-type
Dynamic: home-page
Dynamic: keywords
Dynamic: license
Dynamic: project-url
Dynamic: requires-dist
Dynamic: requires-python
Dynamic: summary
